AUTHORS
LICENSE
MANIFEST.in
README.rst
setup.py
cmsplugin_wunderground/__init__.py
cmsplugin_wunderground/cms_plugins.py
cmsplugin_wunderground/templates/cmsplugin_wunderground/.local_weather.html.swp
cmsplugin_wunderground/templates/cmsplugin_wunderground/local_weather.html
django_cms_wunderground.egg-info/PKG-INFO
django_cms_wunderground.egg-info/SOURCES.txt
django_cms_wunderground.egg-info/dependency_links.txt
django_cms_wunderground.egg-info/not-zip-safe
django_cms_wunderground.egg-info/requires.txt
django_cms_wunderground.egg-info/top_level.txt