Metadata-Version: 1.0
Name: django-cms-wunderground
Version: 1.0.0
Summary: An extension for Django CMS that displays the current local weather pulled from  wunderground.com
Home-page: http://github.com/megamark16/django-cms-wunderground
Author: Mark Ransom
Author-email: megamark16@gmail.com
License: BSD
Platform: OS Independent
Classifier: Development Status :: 4 - Beta
Classifier: Framework :: Django
Classifier: Intended Audience :: Developers
Classifier: License :: OSI Approved :: BSD License
Classifier: Operating System :: OS Independent
Classifier: Programming Language :: Python
Classifier: Topic :: Internet :: WWW/HTTP
Classifier: Topic :: Internet :: WWW/HTTP :: Dynamic Content
